LICENSE.txt
MANIFEST.in
README.md
setup.py
lectric/VERSION
lectric/__init__.py
lectric/client.py
lectric/errors.py
lectric/helpers.py
lectric/lectric_client.py
lectric/lectric_types.py
lectric/py.typed
lectric/types.py
lectric/api/__init__.py
lectric/api/collection/__init__.py
lectric/api/collection/create_collection_collection_create_post.py
lectric/api/collection/delete_entities_collection_entities_delete.py
lectric/api/collection/drop_collection_collection_delete.py
lectric/api/collection/exists_collection_collection_exists_name_get.py
lectric/api/collection/get_collection_collection_get_name_get.py
lectric/api/collection/get_indexes_collection_indexes_name_get.py
lectric/api/collection/get_url_collection_get_url_get.py
lectric/api/collection/is_empty_collection_collection_empty_name_get.py
lectric/api/collection/list_collections_collection_list_get.py
lectric/api/collection/sample_collection_sample_get.py
lectric/api/collection/sizeof_collection_collection_size_name_get.py
lectric/api/default/__init__.py
lectric/api/default/list_connections_connections_get.py
lectric/api/default/root_auth_auth_get.py
lectric/api/default/root_get.py
lectric/api/exact/__init__.py
lectric/api/exact/create_collection_exact_create_collection_post.py
lectric/api/exact/dupes_list_exact_counter_dupes_get.py
lectric/api/exact/get_available_algos_exact_algos_get.py
lectric/api/exact/get_collection_metadata_exact_collection_metadata_get.py
lectric/api/exact/get_exact_collection_entries_exact_collection_entries_get.py
lectric/api/exact/get_ttls_exact_ttls_collection_name_get.py
lectric/api/exact/hard_delete_collection_exact_collection_hard_delete_delete.py
lectric/api/exact/hard_delete_entries_by_file_exact_entries_by_file_hard_delete_delete.py
lectric/api/exact/hard_delete_entries_exact_entries_hard_delete_delete.py
lectric/api/exact/has_dupecounter_exact_dupecounter_get.py
lectric/api/exact/has_revlookup_exact_revlookup_get.py
lectric/api/exact/info_exact_info_get.py
lectric_sdk.egg-info/PKG-INFO
lectric_sdk.egg-info/SOURCES.txt
lectric_sdk.egg-info/dependency_links.txt
lectric_sdk.egg-info/not-zip-safe
lectric_sdk.egg-info/requires.txt
lectric_sdk.egg-info/top_level.txt
