Metadata-Version: 2.2
Name: lectric-sdk
Version: 0.0.47
Summary: Lectric client
Author: Disa Mhembere
Author-email: disamhembere@microsoft.com
Keywords: lectric,vdb,vector database
Classifier: Programming Language :: Python :: 3
Classifier: Operating System :: OS Independent
License-File: LICENSE.txt
Requires-Dist: setuptools>=41.0.1
Requires-Dist: httpx>=0.23.0
Requires-Dist: attrs>=21.4.0
Requires-Dist: wheel
Requires-Dist: requests
Requires-Dist: numpy
Requires-Dist: python-dateutil
Dynamic: author
Dynamic: author-email
Dynamic: classifier
Dynamic: description
Dynamic: description-content-type
Dynamic: keywords
Dynamic: requires-dist
Dynamic: summary
